LFSR.v
module linear_feedback_shift_register(out, clock, reset, seed, load_seed);
	output out;
	input [31:0] seed;
	input load_seed;
	input reset;
	input clock;
	wire [31:0] flip_flop_outputs;
	wire [31:0] flip_flop_inputs;
	flip_flop flip_flop_instance[31:0] (flip_flop_outputs, clock, reset, flip_flop_inputs);
	one_bit_mux muxes[31:0] (flip_flop_inputs, load_seed, seed, {flip_flop_outputs[30:0], feedback3});
	xor feedback_gate_one(feedback1, flip_flop_outputs[6], flip_flop_outputs[31]);
	xor feedback_gate_two(feedback2, feedback1, flip_flop_outputs[5]);
	xor feedback_gate_three(feedback3, feedback2, flip_flop_outputs[1]);
	assign out = feedback3;
endmodule

module flip_flop(out, clock, reset, in);
	input clock;
	input reset;
	input in;
	output out;
	reg out;
	always @(posedge clock or posedge reset)
	begin

	if (reset)
		out = 0;
	else
		out = in;
	end
endmodule

module one_bit_mux(out, control, input_a, input_b);
	output out;
	reg out;
	input control, input_a, input_b;
	wire not_control;
	always @(control or not_control or input_a or input_b)
		out = (control & input_a) | (not_control & input_b);
		not (not_control, control);
endmodule

wb_lfsr.v
module wb_lfsr(i_clk, i_reset, i_wb_cyc, i_wb_stb, i_wb_we, i_wb_addr, i_wb_data, o_wb_stall, o_wb_data, o_wb_ack);
	input i_clk;
	input i_reset;
	input i_wb_cyc;
	input i_wb_stb;
	input i_wb_we;
	input [2:0] i_wb_addr;
	input[7:0] i_wb_data;

	output o_wb_stall;
	output reg o_wb_ack;
	output reg o_wb_data;

	reg [31:0] seed;
    reg lfsr_reset;
	reg load_seed;
	wire lfsr_out;

	linear_feedback_shift_register FLSR_instance(lfsr_out, i_clk, lfsr_reset, seed, load_seed);

	assign	o_wb_stall = 1'b0;

	always @(posedge i_clk)
	if ((i_wb_stb)&&(i_wb_we)&&(!o_wb_stall)&&(i_wb_cyc))
	begin
		case (i_wb_addr)
			3'b000 :	seed[7:0] <= i_wb_data;
			3'b001 :	seed[15:8] <= i_wb_data;
			3'b010 :	seed[23:16] <= i_wb_data;
			3'b011 :	seed[31:24] <= i_wb_data;
			3'b100 :
			begin
			    lfsr_reset <= i_wb_data[0];
        		load_seed <= i_wb_data[1];
        	end
			default:	seed <= 0;
		endcase
	end

	always @(posedge i_clk)
	if ((i_wb_stb)&&(!i_wb_we)&&(!o_wb_stall)&&(i_wb_cyc))
	begin
        o_wb_data <= lfsr_out;
	end

	initial	o_wb_ack = 1'b0;

	always @(posedge i_clk)
	if (i_reset) begin
		o_wb_ack <= 1'b0;
		seed <= 0;
	end else
		o_wb_ack <= ((i_wb_stb) && (!o_wb_stall));

endmodule

wb_lfsr_test.v

module wb_lfrs_test_harness;
	reg i_clk = 0;
	reg i_reset = 1;
	reg i_wb_cyc = 0;
	reg i_wb_stb = 0;
	reg i_wb_we = 0; 
	reg [2:0] i_wb_addr = 0;
	reg [7:0] i_wb_data = 0;

	wire o_wb_stall;	
	wire o_wb_data;
	wire o_wb_ack;

	wb_lfsr test_wb_lfsr(i_clk, i_reset, i_wb_cyc, i_wb_stb, i_wb_we, i_wb_addr, i_wb_data, o_wb_stall, o_wb_data, o_wb_ack);

	always
		#5 i_clk <= !i_clk;
	initial begin
		// reset lfsr
		$dumpfile("wave_wb.vcd");
		$dumpvars;
		i_clk <= 0;
		i_reset <= 1;
		i_wb_cyc <= 0;
		i_wb_stb <= 0;
		#10 i_reset = 0;
		@ (posedge i_clk);
			i_wb_cyc <= 1;
			i_wb_stb <= 1;
			i_wb_we <= 1;
			i_wb_addr <= 3'b100;
			i_wb_data <= 8'b00000001;
		wait (o_wb_ack == 1'b0);
		@ (posedge i_clk);
		i_wb_cyc <= 1'b0;
		i_wb_stb <= 1'b0;
		i_wb_we <= 1'b0;
		// load seed into mem byte 0
		@ (posedge i_clk);
			i_wb_cyc <= 1'b1;
			i_wb_stb <= 1'b1;
			i_wb_we <= 1'b1;
			i_wb_addr <= 3'b000;
			i_wb_data <= 8'b00010101;
		wait (o_wb_ack == 1'b0);
		@ (posedge i_clk);
			i_wb_cyc <= 1'b0;
			i_wb_stb <= 1'b0;
			i_wb_we <= 1'b0;
		// load seed into mem byte 1
		@ (posedge i_clk);
			i_wb_cyc <= 1'b1;
			i_wb_stb <= 1'b1;
			i_wb_we <= 1'b1;
			i_wb_addr <= 3'b001;
			i_wb_data <= 8'b00001111;
		wait (o_wb_ack == 1'b0);
		@ (posedge i_clk);
			i_wb_cyc <= 1'b0;
			i_wb_stb <= 1'b0;
			i_wb_we <= 1'b0;
		// load seed into mem byte 2
		@ (posedge i_clk);
			i_wb_cyc <= 1'b1;
			i_wb_stb <= 1'b1;
			i_wb_we <= 1'b1;
			i_wb_addr <= 3'b010;
			i_wb_data <= 8'b00100100;
		wait (o_wb_ack == 1'b0);
		@ (posedge i_clk);
			i_wb_cyc <= 1'b0;
			i_wb_stb <= 1'b0;
			i_wb_we <= 1'b0;
		// load seed into mem byte 3
		@ (posedge i_clk);
			i_wb_cyc <= 1'b1;
			i_wb_stb <= 1'b1;
			i_wb_we <= 1'b1;
			i_wb_addr <= 3'b011;
			i_wb_data <= 8'b01100100;
		wait (o_wb_ack == 1'b0);
		@ (posedge i_clk);
			i_wb_cyc <= 1'b0;
			i_wb_stb <= 1'b0;
			i_wb_we <= 1'b0;
		// load seed into lfsr
		@ (posedge i_clk);
			i_wb_cyc <= 1'b1;
			i_wb_stb <= 1'b1;
			i_wb_we <= 1'b1;
			i_wb_addr <= 3'b100;
			i_wb_data <= 8'b00000010;
		wait (o_wb_ack == 1'b0);
		@ (posedge i_clk);
			i_wb_cyc <= 1'b0;
			i_wb_stb <= 1'b0;
			i_wb_we <= 1'b0;
		// load seed into lfsr and exit reset state
		@ (posedge i_clk);
			i_wb_cyc <= 1'b1;
			i_wb_stb <= 1'b1;
			i_wb_we <= 1'b1;
			i_wb_addr <= 3'b100;
			i_wb_data <= 8'b00000000;
		wait (o_wb_ack == 1'b0);
		@ (posedge i_clk);
			i_wb_cyc <= 1'b0;
			i_wb_stb <= 1'b0;
			i_wb_we <= 1'b0;
		@ (posedge i_clk);
			i_wb_cyc <= 1'b1;
			i_wb_stb <= 1'b1;
			i_wb_we <= 1'b0;
		#5000  $finish;
	end
endmodule

wave_wb.vcd
$date
	Sat Aug 26 10:00:03 2023
$end
$version
	Icarus Verilog
$end
$timescale
	1s
$end
$scope module wb_lfrs_test_harness $end
$var wire 1 ! o_wb_stall $end
$var wire 1 " o_wb_data $end
$var wire 1 # o_wb_ack $end
$var reg 1 $ i_clk $end
$var reg 1 % i_reset $end
$var reg 3 & i_wb_addr [2:0] $end
$var reg 1 ' i_wb_cyc $end
$var reg 8 ( i_wb_data [7:0] $end
$var reg 1 ) i_wb_stb $end
$var reg 1 * i_wb_we $end
$scope module test_wb_lfsr $end
$var wire 1 $ i_clk $end
$var wire 1 % i_reset $end
$var wire 3 + i_wb_addr [2:0] $end
$var wire 1 ' i_wb_cyc $end
$var wire 8 , i_wb_data [7:0] $end
$var wire 1 ) i_wb_stb $end
$var wire 1 * i_wb_we $end
$var wire 1 ! o_wb_stall $end
$var wire 1 - lfsr_out $end
$var reg 1 . lfsr_reset $end
$var reg 1 / load_seed $end
$var reg 1 # o_wb_ack $end
$var reg 1 " o_wb_data $end
$var reg 32 0 seed [31:0] $end
$scope module FLSR_instance $end
$var wire 1 $ clock $end
$var wire 1 1 feedback1 $end
$var wire 1 2 feedback2 $end
$var wire 1 3 feedback3 $end
$var wire 1 / load_seed $end
$var wire 1 - out $end
$var wire 1 . reset $end
$var wire 32 4 seed [31:0] $end
$var wire 32 5 flip_flop_outputs [31:0] $end
$var wire 32 6 flip_flop_inputs [31:0] $end
$scope module flip_flop_instance[0] $end
$var wire 1 $ clock $end
$var wire 1 7 in $end
$var wire 1 . reset $end
$var reg 1 8 out $end
$upscope $end
$scope module flip_flop_instance[1] $end
$var wire 1 $ clock $end
$var wire 1 9 in $end
$var wire 1 . reset $end
$var reg 1 : out $end
$upscope $end
$scope module flip_flop_instance[2] $end
$var wire 1 $ clock $end
$var wire 1 ; in $end
$var wire 1 . reset $end
$var reg 1 < out $end
$upscope $end
$scope module flip_flop_instance[3] $end
$var wire 1 $ clock $end
$var wire 1 = in $end
$var wire 1 . reset $end
$var reg 1 > out $end
$upscope $end
$scope module flip_flop_instance[4] $end
$var wire 1 $ clock $end
$var wire 1 ? in $end
$var wire 1 . reset $end
$var reg 1 @ out $end
$upscope $end
$scope module flip_flop_instance[5] $end
$var wire 1 $ clock $end
$var wire 1 A in $end
$var wire 1 . reset $end
$var reg 1 B out $end
$upscope $end
$scope module flip_flop_instance[6] $end
$var wire 1 $ clock $end
$var wire 1 C in $end
$var wire 1 . reset $end
$var reg 1 D out $end
$upscope $end
$scope module flip_flop_instance[7] $end
$var wire 1 $ clock $end
$var wire 1 E in $end
$var wire 1 . reset $end
$var reg 1 F out $end
$upscope $end
$scope module flip_flop_instance[8] $end
$var wire 1 $ clock $end
$var wire 1 G in $end
$var wire 1 . reset $end
$var reg 1 H out $end
$upscope $end
$scope module flip_flop_instance[9] $end
$var wire 1 $ clock $end
$var wire 1 I in $end
$var wire 1 . reset $end
$var reg 1 J out $end
$upscope $end
$scope module flip_flop_instance[10] $end
$var wire 1 $ clock $end
$var wire 1 K in $end
$var wire 1 . reset $end
$var reg 1 L out $end
$upscope $end
$scope module flip_flop_instance[11] $end
$var wire 1 $ clock $end
$var wire 1 M in $end
$var wire 1 . reset $end
$var reg 1 N out $end
$upscope $end
$scope module flip_flop_instance[12] $end
$var wire 1 $ clock $end
$var wire 1 O in $end
$var wire 1 . reset $end
$var reg 1 P out $end
$upscope $end
$scope module flip_flop_instance[13] $end
$var wire 1 $ clock $end
$var wire 1 Q in $end
$var wire 1 . reset $end
$var reg 1 R out $end
$upscope $end
$scope module flip_flop_instance[14] $end
$var wire 1 $ clock $end
$var wire 1 S in $end
$var wire 1 . reset $end
$var reg 1 T out $end
$upscope $end
$scope module flip_flop_instance[15] $end
$var wire 1 $ clock $end
$var wire 1 U in $end
$var wire 1 . reset $end
$var reg 1 V out $end
$upscope $end
$scope module flip_flop_instance[16] $end
$var wire 1 $ clock $end
$var wire 1 W in $end
$var wire 1 . reset $end
$var reg 1 X out $end
$upscope $end
$scope module flip_flop_instance[17] $end
$var wire 1 $ clock $end
$var wire 1 Y in $end
$var wire 1 . reset $end
$var reg 1 Z out $end
$upscope $end
$scope module flip_flop_instance[18] $end
$var wire 1 $ clock $end
$var wire 1 [ in $end
$var wire 1 . reset $end
$var reg 1 \ out $end
$upscope $end
$scope module flip_flop_instance[19] $end
$var wire 1 $ clock $end
$var wire 1 ] in $end
$var wire 1 . reset $end
$var reg 1 ^ out $end
$upscope $end
$scope module flip_flop_instance[20] $end
$var wire 1 $ clock $end
$var wire 1 _ in $end
$var wire 1 . reset $end
$var reg 1 ` out $end
$upscope $end
$scope module flip_flop_instance[21] $end
$var wire 1 $ clock $end
$var wire 1 a in $end
$var wire 1 . reset $end
$var reg 1 b out $end
$upscope $end
$scope module flip_flop_instance[22] $end
$var wire 1 $ clock $end
$var wire 1 c in $end
$var wire 1 . reset $end
$var reg 1 d out $end
$upscope $end
$scope module flip_flop_instance[23] $end
$var wire 1 $ clock $end
$var wire 1 e in $end
$var wire 1 . reset $end
$var reg 1 f out $end
$upscope $end
$scope module flip_flop_instance[24] $end
$var wire 1 $ clock $end
$var wire 1 g in $end
$var wire 1 . reset $end
$var reg 1 h out $end
$upscope $end
$scope module flip_flop_instance[25] $end
$var wire 1 $ clock $end
$var wire 1 i in $end
$var wire 1 . reset $end
$var reg 1 j out $end
$upscope $end
$scope module flip_flop_instance[26] $end
$var wire 1 $ clock $end
$var wire 1 k in $end
$var wire 1 . reset $end
$var reg 1 l out $end
$upscope $end
$scope module flip_flop_instance[27] $end
$var wire 1 $ clock $end
$var wire 1 m in $end
$var wire 1 . reset $end
$var reg 1 n out $end
$upscope $end
$scope module flip_flop_instance[28] $end
$var wire 1 $ clock $end
$var wire 1 o in $end
$var wire 1 . reset $end
$var reg 1 p out $end
$upscope $end
$scope module flip_flop_instance[29] $end
$var wire 1 $ clock $end
$var wire 1 q in $end
$var wire 1 . reset $end
$var reg 1 r out $end
$upscope $end
$scope module flip_flop_instance[30] $end
$var wire 1 $ clock $end
$var wire 1 s in $end
$var wire 1 . reset $end
$var reg 1 t out $end
$upscope $end
$scope module flip_flop_instance[31] $end
$var wire 1 $ clock $end
$var wire 1 u in $end
$var wire 1 . reset $end
$var reg 1 v out $end
$upscope $end
$scope module muxes[0] $end
$var wire 1 / control $end
$var wire 1 w input_a $end
$var wire 1 x input_b $end
$var wire 1 y not_control $end
$var reg 1 z out $end
$upscope $end
$scope module muxes[1] $end
$var wire 1 / control $end
$var wire 1 { input_a $end
$var wire 1 | input_b $end
$var wire 1 } not_control $end
$var reg 1 ~ out $end
$upscope $end
$scope module muxes[2] $end
$var wire 1 / control $end
$var wire 1 !" input_a $end
$var wire 1 "" input_b $end
$var wire 1 #" not_control $end
$var reg 1 $" out $end
$upscope $end
$scope module muxes[3] $end
$var wire 1 / control $end
$var wire 1 %" input_a $end
$var wire 1 &" input_b $end
$var wire 1 '" not_control $end
$var reg 1 (" out $end
$upscope $end
$scope module muxes[4] $end
$var wire 1 / control $end
$var wire 1 )" input_a $end
$var wire 1 *" input_b $end
$var wire 1 +" not_control $end
$var reg 1 ," out $end
$upscope $end
$scope module muxes[5] $end
$var wire 1 / control $end
$var wire 1 -" input_a $end
$var wire 1 ." input_b $end
$var wire 1 /" not_control $end
$var reg 1 0" out $end
$upscope $end
$scope module muxes[6] $end
$var wire 1 / control $end
$var wire 1 1" input_a $end
$var wire 1 2" input_b $end
$var wire 1 3" not_control $end
$var reg 1 4" out $end
$upscope $end
$scope module muxes[7] $end
$var wire 1 / control $end
$var wire 1 5" input_a $end
$var wire 1 6" input_b $end
$var wire 1 7" not_control $end
$var reg 1 8" out $end
$upscope $end
$scope module muxes[8] $end
$var wire 1 / control $end
$var wire 1 9" input_a $end
$var wire 1 :" input_b $end
$var wire 1 ;" not_control $end
$var reg 1 <" out $end
$upscope $end
$scope module muxes[9] $end
$var wire 1 / control $end
$var wire 1 =" input_a $end
$var wire 1 >" input_b $end
$var wire 1 ?" not_control $end
$var reg 1 @" out $end
$upscope $end
$scope module muxes[10] $end
$var wire 1 / control $end
$var wire 1 A" input_a $end
$var wire 1 B" input_b $end
$var wire 1 C" not_control $end
$var reg 1 D" out $end
$upscope $end
$scope module muxes[11] $end
$var wire 1 / control $end
$var wire 1 E" input_a $end
$var wire 1 F" input_b $end
$var wire 1 G" not_control $end
$var reg 1 H" out $end
$upscope $end
$scope module muxes[12] $end
$var wire 1 / control $end
$var wire 1 I" input_a $end
$var wire 1 J" input_b $end
$var wire 1 K" not_control $end
$var reg 1 L" out $end
$upscope $end
$scope module muxes[13] $end
$var wire 1 / control $end
$var wire 1 M" input_a $end
$var wire 1 N" input_b $end
$var wire 1 O" not_control $end
$var reg 1 P" out $end
$upscope $end
$scope module muxes[14] $end
$var wire 1 / control $end
$var wire 1 Q" input_a $end
$var wire 1 R" input_b $end
$var wire 1 S" not_control $end
$var reg 1 T" out $end
$upscope $end
$scope module muxes[15] $end
$var wire 1 / control $end
$var wire 1 U" input_a $end
$var wire 1 V" input_b $end
$var wire 1 W" not_control $end
$var reg 1 X" out $end
$upscope $end
$scope module muxes[16] $end
$var wire 1 / control $end
$var wire 1 Y" input_a $end
$var wire 1 Z" input_b $end
$var wire 1 [" not_control $end
$var reg 1 \" out $end
$upscope $end
$scope module muxes[17] $end
$var wire 1 / control $end
$var wire 1 ]" input_a $end
$var wire 1 ^" input_b $end
$var wire 1 _" not_control $end
$var reg 1 `" out $end
$upscope $end
$scope module muxes[18] $end
$var wire 1 / control $end
$var wire 1 a" input_a $end
$var wire 1 b" input_b $end
$var wire 1 c" not_control $end
$var reg 1 d" out $end
$upscope $end
$scope module muxes[19] $end
$var wire 1 / control $end
$var wire 1 e" input_a $end
$var wire 1 f" input_b $end
$var wire 1 g" not_control $end
$var reg 1 h" out $end
$upscope $end
$scope module muxes[20] $end
$var wire 1 / control $end
$var wire 1 i" input_a $end
$var wire 1 j" input_b $end
$var wire 1 k" not_control $end
$var reg 1 l" out $end
$upscope $end
$scope module muxes[21] $end
$var wire 1 / control $end
$var wire 1 m" input_a $end
$var wire 1 n" input_b $end
$var wire 1 o" not_control $end
$var reg 1 p" out $end
$upscope $end
$scope module muxes[22] $end
$var wire 1 / control $end
$var wire 1 q" input_a $end
$var wire 1 r" input_b $end
$var wire 1 s" not_control $end
$var reg 1 t" out $end
$upscope $end
$scope module muxes[23] $end
$var wire 1 / control $end
$var wire 1 u" input_a $end
$var wire 1 v" input_b $end
$var wire 1 w" not_control $end
$var reg 1 x" out $end
$upscope $end
$scope module muxes[24] $end
$var wire 1 / control $end
$var wire 1 y" input_a $end
$var wire 1 z" input_b $end
$var wire 1 {" not_control $end
$var reg 1 |" out $end
$upscope $end
$scope module muxes[25] $end
$var wire 1 / control $end
$var wire 1 }" input_a $end
$var wire 1 ~" input_b $end
$var wire 1 !# not_control $end
$var reg 1 "# out $end
$upscope $end
$scope module muxes[26] $end
$var wire 1 / control $end
$var wire 1 ## input_a $end
$var wire 1 $# input_b $end
$var wire 1 %# not_control $end
$var reg 1 &# out $end
$upscope $end
$scope module muxes[27] $end
$var wire 1 / control $end
$var wire 1 '# input_a $end
$var wire 1 (# input_b $end
$var wire 1 )# not_control $end
$var reg 1 *# out $end
$upscope $end
$scope module muxes[28] $end
$var wire 1 / control $end
$var wire 1 +# input_a $end
$var wire 1 ,# input_b $end
$var wire 1 -# not_control $end
$var reg 1 .# out $end
$upscope $end
$scope module muxes[29] $end
$var wire 1 / control $end
$var wire 1 /# input_a $end
$var wire 1 0# input_b $end
$var wire 1 1# not_control $end
$var reg 1 2# out $end
$upscope $end
$scope module muxes[30] $end
$var wire 1 / control $end
$var wire 1 3# input_a $end
$var wire 1 4# input_b $end
$var wire 1 5# not_control $end
$var reg 1 6# out $end
$upscope $end
$scope module muxes[31] $end
$var wire 1 / control $end
$var wire 1 7# input_a $end
$var wire 1 8# input_b $end
$var wire 1 9# not_control $end
$var reg 1 :# out $end
$upscope $end
$upscope $end
$upscope $end
$upscope $end
$enddefinitions $end
#0
$dumpvars
x:#
x9#
x8#
x7#
x6#
x5#
x4#
x3#
x2#
x1#
x0#
x/#
x.#
x-#
x,#
x+#
x*#
x)#
x(#
x'#
x&#
x%#
x$#
x##
x"#
x!#
x~"
x}"
x|"
x{"
xz"
xy"
xx"
xw"
xv"
xu"
xt"
xs"
xr"
xq"
xp"
xo"
xn"
xm"
xl"
xk"
xj"
xi"
xh"
xg"
xf"
xe"
xd"
xc"
xb"
xa"
x`"
x_"
x^"
x]"
x\"
x["
xZ"
xY"
xX"
xW"
xV"
xU"
xT"
xS"
xR"
xQ"
xP"
xO"
xN"
xM"
xL"
xK"
xJ"
xI"
xH"
xG"
xF"
xE"
xD"
xC"
xB"
xA"
x@"
x?"
x>"
x="
x<"
x;"
x:"
x9"
x8"
x7"
x6"
x5"
x4"
x3"
x2"
x1"
x0"
x/"
x."
x-"
x,"
x+"
x*"
x)"
x("
x'"
x&"
x%"
x$"
x#"
x""
x!"
x~
x}
x|
x{
xz
xy
xx
xw
xv
xu
xt
xs
xr
xq
xp
xo
xn
xm
xl
xk
xj
xi
xh
xg
xf
xe
xd
xc
xb
xa
x`
x_
x^
x]
x\
x[
xZ
xY
xX
xW
xV
xU
xT
xS
xR
xQ
xP
xO
xN
xM
xL
xK
xJ
xI
xH
xG
xF
xE
xD
xC
xB
xA
x@
x?
x>
x=
x<
x;
x:
x9
x8
x7
bx 6
bx 5
bx 4
x3
x2
x1
bx 0
x/
x.
x-
b0 ,
b0 +
0*
0)
b0 (
0'
b0 &
1%
0$
0#
x"
0!
$end
#5
1$
#10
0$
0%
#15
b1 (
b1 ,
b100 &
b100 +
1*
1)
1'
1$
#20
0$
#25
07
0z
0x
0-
03
09
0;
0=
0?
0A
0C
0E
0G
0I
0K
0M
0O
0Q
0S
0U
0W
0Y
0[
0]
0_
0a
0c
0e
0g
0i
0k
0m
0o
0q
0s
0u
02
0~
0$"
0("
0,"
00"
04"
08"
0<"
0@"
0D"
0H"
0L"
0P"
0T"
0X"
0\"
0`"
0d"
0h"
0l"
0p"
0t"
0x"
0|"
0"#
0&#
0*#
0.#
02#
06#
b0 6
0:#
01
0|
0""
0&"
0*"
0."
02"
06"
0:"
0>"
0B"
0F"
0J"
0N"
0R"
0V"
0Z"
0^"
0b"
0f"
0j"
0n"
0r"
0v"
0z"
0~"
0$#
0(#
0,#
00#
04#
08#
1y
1}
1#"
1'"
1+"
1/"
13"
17"
1;"
1?"
1C"
1G"
1K"
1O"
1S"
1W"
1["
1_"
1c"
1g"
1k"
1o"
1s"
1w"
1{"
1!#
1%#
1)#
1-#
11#
15#
19#
0v
0t
0r
0p
0n
0l
0j
0h
0f
0d
0b
0`
0^
0\
0Z
0X
0V
0T
0R
0P
0N
0L
0J
0H
0F
0D
0B
0@
0>
0<
0:
b0 5
08
0*
0)
0'
0/
1.
1#
1$
#30
0$
#35
0#
b10101 (
b10101 ,
b0 &
b0 +
1*
1)
1'
1$
#40
0$
#45
1w
0{
1!"
0%"
1)"
0-"
01"
05"
bx00010101 0
bx00010101 4
1#
0*
0)
0'
1$
#50
0$
#55
b1111 (
b1111 ,
b1 &
b1 +
1*
1)
1'
0#
1$
#60
0$
#65
19"
1="
1A"
1E"
0I"
0M"
0Q"
0U"
bx0000111100010101 0
bx0000111100010101 4
1#
0*
0)
0'
1$
#70
0$
#75
b100100 (
b100100 ,
b10 &
b10 +
1*
1)
1'
0#
1$
#80
0$
#85
0Y"
0]"
1a"
0e"
0i"
1m"
0q"
0u"
bx001001000000111100010101 0
bx001001000000111100010101 4
1#
0*
0)
0'
1$
#90
0$
#95
b1100100 (
b1100100 ,
b11 &
b11 +
1*
1)
1'
0#
1$
#100
0$
#105
0y"
0}"
1##
0'#
0+#
1/#
13#
07#
b1100100001001000000111100010101 0
b1100100001001000000111100010101 4
1#
0*
0)
0'
1$
#110
0$
#115
b10 (
b10 ,
b100 &
b100 +
1*
1)
1'
0#
1$
#120
0$
#125
17
1;
1?
1G
1I
1K
1M
1[
1a
1k
1q
1s
0y
1z
0}
0#"
1$"
0'"
0+"
1,"
0/"
03"
07"
0;"
1<"
0?"
1@"
0C"
1D"
0G"
1H"
0K"
0O"
0S"
0W"
0["
0_"
0c"
1d"
0g"
0k"
0o"
1p"
0s"
0w"
0{"
0!#
0%#
1&#
0)#
0-#
01#
12#
05#
b1100100001001000000111100010101 6
16#
09#
1/
0.
1#
0*
0)
0'
1$
#130
0$
#135
b0 (
b0 ,
1*
1)
1'
0#
1|
1&"
1."
1>"
1B"
1F"
1J"
1f"
1r"
1(#
14#
18#
18
1<
1@
1H
1J
1L
1N
1\
1b
1l
1r
b1100100001001000000111100010101 5
1t
1$
#140
0$
#145
19
1=
1A
1O
1]
1c
1m
1u
07
1~
0;
1("
0?
10"
0G
1I
1K
1M
1L"
0[
1h"
0a
1t"
0k
1*#
0q
1s
1:#
1y
0z
1}
1#"
0$"
1'"
1+"
0,"
1/"
13"
17"
1;"
0<"
1?"
1@"
1C"
1D"
1G"
1H"
1K"
1O"
1S"
1W"
1["
1_"
1c"
0d"
1g"
1k"
1o"
0p"
1s"
1w"
1{"
1!#
1%#
0&#
1)#
1-#
11#
02#
15#
b11001000010010000001111000101010 6
16#
19#
0/
1#
0*
0)
0'
1$
#150
0$
#155
1)
1'
0#
17
1z
09
1;
0=
1?
0A
1C
0I
1Q
0]
1_
0c
1e
0m
1o
0s
1x
0~
1$"
0("
1,"
00"
14"
0@"
1P"
0h"
1l"
0t"
1x"
0*#
1.#
b10010000100100000011110001010101 6
06#
1-
13
0|
1""
0&"
1*"
0."
12"
0>"
1N"
0f"
1j"
0r"
1v"
0(#
1,#
04#
11
08
1:
0<
1>
0@
1B
0H
1P
0\
1^
0b
1d
0l
1n
0r
b11001000010010000001111000101010 5
1v
1$
#160
0$
#165
1"
1#
07
0z
19
0;
1=
0?
1A
0C
1E
0K
1S
0_
1a
0e
1g
0o
1q
0u
0x
1~
0$"
1("
0,"
10"
04"
18"
0D"
1T"
0l"
1p"
0x"
1|"
0.#
12#
b100001001000000111100010101010 6
0:#
01
02
0-
03
1|
0""
1&"
0*"
1."
02"
16"
0B"
1R"
0j"
1n"
0v"
1z"
0,#
10#
08#
0t
1p
0n
1f
0d
1`
0^
1R
0J
1D
0B
1@
0>
1<
0:
b10010000100100000011110001010101 5
18
1$
#170
0$
#175
0"
09
1;
0=
1?
0A
1C
0E
1G
0M
1U
0a
1c
0g
1i
0q
1s
0~
1$"
0("
1,"
00"
14"
08"
1<"
0H"
1X"
0p"
1t"
0|"
1"#
02#
b1000010010000001111000101010100 6
16#
12
0|
1""
0&"
1*"
0."
12"
06"
1:"
0F"
1V"
0n"
1r"
0z"
1~"
00#
14#
08
1:
0<
1>
0@
1B
0D
1F
0L
1T
0`
1b
0f
1h
0p
1r
b100001001000000111100010101010 5
0v
1$
#180
0$
#185
17
0;
1=
0?
1A
0C
1E
0G
1I
0O
1W
0c
1e
0i
1k
0s
1u
1z
0$"
1("
0,"
10"
04"
18"
0<"
1@"
0L"
1\"
0t"
1x"
0"#
1&#
06#
b10000100100000011110001010101001 6
1:#
1x
11
12
0""
1&"
0*"
1."
02"
16"
0:"
1>"
0J"
1Z"
0r"
1v"
0~"
1$#
04#
18#
1-
13
1t
0r
1j
0h
1d
0b
1V
0N
1H
0F
1D
0B
1@
0>
1<
b1000010010000001111000101010100 5
0:
1$
#190
0$
#195
1"
07
0z
0x
19
0=
1?
0A
1C
0E
1G
0I
1K
0Q
1Y
0e
1g
0k
1m
0u
0-
03
1~
0("
1,"
00"
14"
08"
1<"
0@"
1D"
0P"
1`"
0x"
1|"
0&#
1*#
b1001000000111100010101010010 6
0:#
02
1|
0&"
1*"
0."
12"
06"
1:"
0>"
1B"
0N"
1^"
0v"
1z"
0$#
1(#
08#
18
0<
1>
0@
1B
0D
1F
0H
1J
0P
1X
0d
1f
0j
1l
0t
b10000100100000011110001010101001 5
1v
1$
#200
0$
#205
0"
07
0z
09
1;
0?
1A
0C
1E
0G
1I
0K
1M
0S
1[
0g
1i
0m
1o
0x
0~
1$"
0,"
10"
04"
18"
0<"
1@"
0D"
1H"
0T"
1d"
0|"
1"#
0*#
b10010000001111000101010100100 6
1.#
12
0-
03
0|
1""
0*"
1."
02"
16"
0:"
1>"
0B"
1F"
0R"
1b"
0z"
1~"
0(#
1,#
0v
1n
0l
1h
0f
1Z
0R
1L
0J
1H
0F
1D
0B
1@
0>
1:
b1001000000111100010101010010 5
08
1$
#210
0$
#215
17
1z
0;
1=
0A
1C
0E
1G
0I
1K
0M
1O
0U
1]
0i
1k
0o
1q
1x
0$"
1("
00"
14"
08"
1<"
0@"
1D"
0H"
1L"
0X"
1h"
0"#
1&#
0.#
b100100000011110001010101001001 6
12#
1-
13
01
0""
1&"
0."
12"
06"
1:"
0>"
1B"
0F"
1J"
0V"
1f"
0~"
1$#
0,#
10#
0:
1<
0@
1B
0D
1F
0H
1J
0L
1N
0T
1\
0h
1j
0n
b10010000001111000101010100100 5
1p
1$
#220
0$
#225
1"
17
1z
1x
19
0=
1?
0C
1E
0G
1I
0K
1M
0O
1Q
0W
1_
0k
1m
0q
1s
1-
13
1~
0("
1,"
04"
18"
0<"
1@"
0D"
1H"
0L"
1P"
0\"
1l"
0&#
1*#
02#
b1001000000111100010101010010011 6
16#
11
12
1|
0&"
1*"
02"
16"
0:"
1>"
0B"
1F"
0J"
1N"
0Z"
1j"
0$#
1(#
00#
14#
1r
0p
1l
0j
1^
0V
1P
0N
1L
0J
1H
0F
1D
0B
1>
0<
b100100000011110001010101001001 5
18
1$
#230
0$
#235
17
1z
1;
0?
1A
0E
1G
0I
1K
0M
1O
0Q
1S
0Y
1a
0m
1o
0s
1u
1x
02
1$"
0,"
10"
08"
1<"
0@"
1D"
0H"
1L"
0P"
1T"
0`"
1p"
0*#
1.#
06#
b10010000001111000101010100100111 6
1:#
1-
13
01
1""
0*"
1."
06"
1:"
0>"
1B"
0F"
1J"
0N"
1R"
0^"
1n"
0(#
1,#
04#
18#
1:
0>
1@
0D
1F
0H
1J
0L
1N
0P
1R
0X
1`
0l
1n
0r
b1001000000111100010101010010011 5
1t
1$
#240
0$
#245
17
1z
1x
1=
0A
1C
0G
1I
0K
1M
0O
1Q
0S
1U
0[
1c
0o
1q
0u
1-
13
1("
00"
14"
0<"
1@"
0D"
1H"
0L"
1P"
0T"
1X"
0d"
1t"
0.#
12#
b100000011110001010101001001111 6
0:#
11
02
1&"
0."
12"
0:"
1>"
0B"
1F"
0J"
1N"
0R"
1V"
0b"
1r"
0,#
10#
08#
1v
0t
1p
0n
1b
0Z
1T
0R
1P
0N
1L
0J
1H
0F
1B
0@
b10010000001111000101010100100111 5
1<
1$
#250
0$
#255
07
0z
0x
1?
0C
1E
0I
1K
0M
1O
0Q
1S
0U
1W
0]
1e
0q
1s
0-
03
1,"
04"
18"
0@"
1D"
0H"
1L"
0P"
1T"
0X"
1\"
0h"
1x"
02#
b1000000111100010101010010011110 6
16#
12
1*"
02"
16"
0>"
1B"
0F"
1J"
0N"
1R"
0V"
1Z"
0f"
1v"
00#
14#
1>
0B
1D
0H
1J
0L
1N
0P
1R
0T
1V
0\
1d
0p
1r
b100000011110001010101001001111 5
0v
1$
#260
0$
